annotation_protocol/__init__.py
annotation_protocol/_version.py
annotation_protocol/annotation_protocol.py
annotation_protocol/check_annotations.py
annotation_protocol/utils.py
annotation_protocol-1.4.0.dist-info/licenses/LICENSE
annotation_protocol-1.4.0.dist-info/METADATA
annotation_protocol-1.4.0.dist-info/WHEEL
annotation_protocol-1.4.0.dist-info/top_level.txt
annotation_protocol-1.4.0.dist-info/RECORD
