Metadata-Version: 2.4
Name: annotation_protocol
Version: 1.4.0
Summary: Annotation protocol to allow very thorough isinstance checks.
Maintainer-email: Ruud Kassing <ruud.kassing@haskoning.com>, Miguel Pereira Hernandez <miguel.hernandez@haskoning.com>, Pierpaolo Lucarelli <pierpaolo.lucarelli@haskoning.com>, Adjorn van Engelenhoven <adjorn.van.engelenhoven@haskoning.com>
License: MIT
Classifier: Programming Language :: Python :: 3
Classifier: Programming Language :: Python :: 3 :: Only
Classifier: Programming Language :: Python :: 3.10
Classifier: Programming Language :: Python :: 3.11
Classifier: Programming Language :: Python :: 3.12
Classifier: License :: OSI Approved :: MIT License
Classifier: Operating System :: OS Independent
Requires-Python: <=3.13,>=3.10
License-File: LICENSE
Provides-Extra: dev
Requires-Dist: pytest; extra == "dev"
Requires-Dist: black; extra == "dev"
Requires-Dist: pre-commit; extra == "dev"
Requires-Dist: isort; extra == "dev"
Requires-Dist: bandit==1.7.0; extra == "dev"
Requires-Dist: flake8; extra == "dev"
Dynamic: license-file
